CHANGELOG.txt
License.txt
MANIFEST.in
readme.txt
setup.py
rsa_algo_madhusree/__init__.py
rsa_algo_madhusree.egg-info/PKG-INFO
rsa_algo_madhusree.egg-info/SOURCES.txt
rsa_algo_madhusree.egg-info/dependency_links.txt
rsa_algo_madhusree.egg-info/top_level.txt