Metadata-Version: 1.1
Name: rsa-algo-madhusree
Version: 0.0.1
Summary: Encryption and Decryption of plain text using RSA Algorithm
Home-page: UNKNOWN
Author: Madhusree Rana
Author-email: madhusree.rana2017@gmail.com
License: MIT
Keywords: RSA
Platform: UNKNOWN
Classifier: Development Status :: 5 - Production/Stable
Classifier: Intended Audience :: Education
Classifier: Operating System :: Microsoft :: Windows :: Windows 10
Classifier: License :: OSI Approved :: MIT License
Classifier: Programming Language :: Python :: 3
